litestar/__init__.py
litestar/__main__.py
litestar/_multipart.py
litestar/_parsers.py
litestar/app.py
litestar/background_tasks.py
litestar/concurrency.py
litestar/constants.py
litestar/controller.py
litestar/data_extractors.py
litestar/di.py
litestar/enums.py
litestar/file_system.py
litestar/pagination.py
litestar/params.py
litestar/py.typed
litestar/router.py
litestar/status_codes.py
litestar/typing.py
litestar/_asgi/__init__.py
litestar/_asgi/asgi_router.py
litestar/_asgi/utils.py
litestar/_asgi/routing_trie/__init__.py
litestar/_asgi/routing_trie/mapping.py
litestar/_asgi/routing_trie/traversal.py
litestar/_asgi/routing_trie/types.py
litestar/_asgi/routing_trie/validate.py
litestar/_kwargs/__init__.py
litestar/_kwargs/cleanup.py
litestar/_kwargs/dependencies.py
litestar/_kwargs/extractors.py
litestar/_kwargs/kwargs_model.py
litestar/_kwargs/parameter_definition.py
litestar/_kwargs/types.py
litestar/_layers/__init__.py
litestar/_layers/utils.py
litestar/_openapi/__init__.py
litestar/_openapi/datastructures.py
litestar/_openapi/parameters.py
litestar/_openapi/path_item.py
litestar/_openapi/plugin.py
litestar/_openapi/request_body.py
litestar/_openapi/responses.py
litestar/_openapi/utils.py
litestar/_openapi/schema_generation/__init__.py
litestar/_openapi/schema_generation/constrained_fields.py
litestar/_openapi/schema_generation/examples.py
litestar/_openapi/schema_generation/schema.py
litestar/_openapi/schema_generation/utils.py
litestar/_openapi/schema_generation/plugins/__init__.py
litestar/_openapi/schema_generation/plugins/dataclass.py
litestar/_openapi/schema_generation/plugins/pagination.py
litestar/_openapi/schema_generation/plugins/struct.py
litestar/_openapi/schema_generation/plugins/typed_dict.py
litestar/_openapi/typescript_converter/__init__.py
litestar/_openapi/typescript_converter/converter.py
litestar/_openapi/typescript_converter/schema_parsing.py
litestar/_openapi/typescript_converter/types.py
litestar/_signature/__init__.py
litestar-2.15.0.dist-info/METADATA
litestar-2.15.0.dist-info/WHEEL
litestar-2.15.0.dist-info/entry_points.txt
litestar-2.15.0.dist-info/licenses/LICENSE
litestar-2.15.0.dist-info/RECORD
