Metadata-Version: 2.4
Name: litestar
Version: 2.15.0
Summary: Litestar - A production-ready, highly performant, extensible ASGI API Framework
Project-URL: Blog, https://blog.litestar.dev
Project-URL: Changelog, https://github.com/litestar-org/litestar/releases/
Project-URL: Discord, https://discord.gg/litestar
Project-URL: Documentation, https://docs.litestar.dev/
Project-URL: Homepage, https://litestar.dev/
Project-URL: Issue Tracker, https://github.com/litestar-org/litestar/issues?q=is%3Aissue+is%3Aopen+sort%3Aupdated-desc
Project-URL: Reddit, https://www.reddit.com/r/LitestarAPI
Project-URL: Repository, https://github.com/litestar-org/litestar
Project-URL: Twitter, https://twitter.com/LitestarAPI
Project-URL: Funding, https://github.com/sponsors/litestar-org
Project-URL: Discussions, https://github.com/litestar-org/litestar/discussions
Author-email: Cody Fincher <cody@litestar.dev>, Jacob Coffee <jacob@litestar.dev>, Janek Nouvertné <janek@litestar.dev>, Na'aman Hirschfeld <nhirschfeld@gmail.com>, Peter Schutt <peter@litestar.dev>
Maintainer-email: Litestar Developers <hello@litestar.dev>, Cody Fincher <cody@litestar.dev>, Jacob Coffee <jacob@litestar.dev>, Janek Nouvertné <janek@litestar.dev>, Peter Schutt <peter@litestar.dev>, Visakh Unnikrishnan <guacs@litestar.dev>, Alc <alc@litestar.dev>
License: MIT
License-File: LICENSE
Keywords: api,asgi,litestar,rest,starlite
Classifier: Development Status :: 5 - Production/Stable
Classifier: Environment :: Web Environment
Classifier: Intended Audience :: Developers
Classifier: Intended Audience :: Information Technology
Classifier: Intended Audience :: System Administrators
Classifier: License :: OSI Approved :: MIT License
Classifier: Natural Language :: English
Classifier: Operating System :: OS Independent
Classifier: Programming Language :: Python
Classifier: Programming Language :: Python :: 3.8
Classifier: Programming Language :: Python :: 3.9
Classifier: Programming Language :: Python :: 3.10
Classifier: Programming Language :: Python :: 3.11
Classifier: Programming Language :: Python :: 3.12
Classifier: Programming Language :: Python :: 3.13
Classifier: Topic :: Internet
Classifier: Topic :: Internet :: WWW/HTTP
Classifier: Topic :: Internet :: WWW/HTTP :: HTTP Servers
Classifier: Topic :: Software Development
Classifier: Topic :: Software Development :: Libraries
Classifier: Topic :: Software Development :: Libraries :: Application Frameworks
Classifier: Topic :: Software Development :: Libraries :: Python Modules
Classifier: Typing :: Typed
Requires-Python: <4.0,>=3.8
Requires-Dist: anyio>=3
Requires-Dist: click
Requires-Dist: exceptiongroup; python_version < '3.11'
Requires-Dist: httpx>=0.22
Requires-Dist: importlib-metadata; python_version < '3.10'
Requires-Dist: importlib-resources>=5.12.0; python_version < '3.9'
Requires-Dist: litestar-htmx>=0.4.0
Requires-Dist: msgspec>=0.18.2
Requires-Dist: multidict>=6.0.2
Requires-Dist: multipart>=1.2.0
Requires-Dist: polyfactory>=2.6.3
Requires-Dist: pyyaml
Requires-Dist: rich-click
Requires-Dist: rich>=13.0.0
Requires-Dist: typing-extensions
Provides-Extra: annotated-types
Requires-Dist: annotated-types; extra == 'annotated-types'
Provides-Extra: attrs
Requires-Dist: attrs; extra == 'attrs'
Provides-Extra: brotli
Requires-Dist: brotli; extra == 'brotli'
Provides-Extra: cli
Requires-Dist: jsbeautifier; extra == 'cli'
Requires-Dist: uvicorn[standard]; extra == 'cli'
Requires-Dist: uvloop>=0.18.0; (sys_platform != 'win32') and extra == 'cli'
Provides-Extra: cryptography
Requires-Dist: cryptography; extra == 'cryptography'
Provides-Extra: full
Requires-Dist: advanced-alchemy>=0.2.2; extra == 'full'
Requires-Dist: annotated-types; extra == 'full'
Requires-Dist: attrs; extra == 'full'
Requires-Dist: brotli; extra == 'full'
Requires-Dist: cryptography; extra == 'full'
Requires-Dist: email-validator; extra == 'full'
Requires-Dist: fast-query-parsers>=1.0.2; extra == 'full'
Requires-Dist: jinja2; extra == 'full'
Requires-Dist: jinja2>=3.1.2; extra == 'full'
Requires-Dist: jsbeautifier; extra == 'full'
Requires-Dist: mako>=1.2.4; extra == 'full'
Requires-Dist: minijinja>=1.0.0; extra == 'full'
Requires-Dist: opentelemetry-instrumentation-asgi; extra == 'full'
Requires-Dist: piccolo; extra == 'full'
Requires-Dist: picologging; (python_version < '3.13') and extra == 'full'
Requires-Dist: prometheus-client; extra == 'full'
Requires-Dist: pydantic; extra == 'full'
Requires-Dist: pydantic-extra-types!=2.9.0; (python_version < '3.9') and extra == 'full'
Requires-Dist: pydantic-extra-types; (python_version >= '3.9') and extra == 'full'
Requires-Dist: pyjwt>=2.9.0; extra == 'full'
Requires-Dist: redis[hiredis]>=4.4.4; extra == 'full'
Requires-Dist: structlog; extra == 'full'
Requires-Dist: uvicorn[standard]; extra == 'full'
Requires-Dist: uvloop>=0.18.0; (sys_platform != 'win32') and extra == 'full'
Requires-Dist: valkey[libvalkey]>=6.0.2; extra == 'full'
Provides-Extra: jinja
Requires-Dist: jinja2>=3.1.2; extra == 'jinja'
Provides-Extra: jwt
Requires-Dist: cryptography; extra == 'jwt'
Requires-Dist: pyjwt>=2.9.0; extra == 'jwt'
Provides-Extra: mako
Requires-Dist: mako>=1.2.4; extra == 'mako'
Provides-Extra: minijinja
Requires-Dist: minijinja>=1.0.0; extra == 'minijinja'
Provides-Extra: opentelemetry
Requires-Dist: opentelemetry-instrumentation-asgi; extra == 'opentelemetry'
Provides-Extra: piccolo
Requires-Dist: piccolo; extra == 'piccolo'
Provides-Extra: picologging
Requires-Dist: picologging; (python_version < '3.13') and extra == 'picologging'
Provides-Extra: prometheus
Requires-Dist: prometheus-client; extra == 'prometheus'
Provides-Extra: pydantic
Requires-Dist: email-validator; extra == 'pydantic'
Requires-Dist: pydantic; extra == 'pydantic'
Requires-Dist: pydantic-extra-types!=2.9.0; (python_version < '3.9') and extra == 'pydantic'
Requires-Dist: pydantic-extra-types; (python_version >= '3.9') and extra == 'pydantic'
Provides-Extra: redis
Requires-Dist: redis[hiredis]>=4.4.4; extra == 'redis'
Provides-Extra: sqlalchemy
Requires-Dist: advanced-alchemy>=0.2.2; extra == 'sqlalchemy'
Provides-Extra: standard
Requires-Dist: fast-query-parsers>=1.0.2; extra == 'standard'
Requires-Dist: jinja2; extra == 'standard'
Requires-Dist: jsbeautifier; extra == 'standard'
Requires-Dist: uvicorn[standard]; extra == 'standard'
Requires-Dist: uvloop>=0.18.0; (sys_platform != 'win32') and extra == 'standard'
Provides-Extra: structlog
Requires-Dist: structlog; extra == 'structlog'
Provides-Extra: valkey
Requires-Dist: valkey[libvalkey]>=6.0.2; extra == 'valkey'
